qulacs_core.cpython-312-x86_64-linux-gnu.so
qulacs/__init__.py
qulacs/__init__.pyi
qulacs/_version.py
qulacs/circuit.pyi
qulacs/gate.pyi
qulacs/observable.pyi
qulacs/py.typed
qulacs/quantum_operator.pyi
qulacs/state.pyi
qulacs/circuit/__init__.py
qulacs/circuit/__init__.pyi
qulacs/circuit/py.typed
qulacs/converter/__init__.py
qulacs/converter/qasm_converter.py
qulacs/gate/__init__.py
qulacs/gate/__init__.pyi
qulacs/gate/py.typed
qulacs/observable/__init__.py
qulacs/observable/__init__.pyi
qulacs/observable/py.typed
qulacs/quantum_operator/__init__.py
qulacs/quantum_operator/__init__.pyi
qulacs/quantum_operator/py.typed
qulacs/state/__init__.py
qulacs/state/__init__.pyi
qulacs/state/py.typed
qulacs/utils/__init__.py
qulacs/utils/conversions_openfermion.py
qulacs/vistest/__init__.py
qulacs/vistest/test_vis.py
qulacs/visualizer/__init__.py
qulacs/visualizer/visualizer.py
qulacs.libs/libgomp-a34b3233.so.1.0.0
qulacs-0.6.12.dist-info/METADATA
qulacs-0.6.12.dist-info/WHEEL
qulacs-0.6.12.dist-info/top_level.txt
qulacs-0.6.12.dist-info/RECORD
qulacs-0.6.12.dist-info/licenses/LICENSE
