Metadata-Version: 2.4
Name: qulacs
Version: 0.6.12
Summary: Quantum circuit simulator for research
Author-email: QunaSys <qulacs@qunasys.com>
License-Expression: MIT
Project-URL: homepage, http://docs.qulacs.org
Classifier: Development Status :: 3 - Alpha
Classifier: Environment :: Console
Classifier: Intended Audience :: Science/Research
Classifier: Operating System :: MacOS :: MacOS X
Classifier: Operating System :: Microsoft :: Windows
Classifier: Operating System :: POSIX
Classifier: Programming Language :: Python
Classifier: Topic :: Communications :: Email
License-File: LICENSE
Requires-Dist: numpy
Requires-Dist: scipy
Provides-Extra: dev
Requires-Dist: black; extra == "dev"
Requires-Dist: flake8; extra == "dev"
Requires-Dist: isort; extra == "dev"
Requires-Dist: mypy; extra == "dev"
Requires-Dist: pybind11-stubgen; extra == "dev"
Requires-Dist: openfermion; extra == "dev"
Requires-Dist: pytest; extra == "dev"
Provides-Extra: test
Requires-Dist: openfermion; extra == "test"
Provides-Extra: ci
Requires-Dist: black; extra == "ci"
Requires-Dist: flake8; extra == "ci"
Requires-Dist: isort; extra == "ci"
Requires-Dist: mypy; extra == "ci"
Requires-Dist: pybind11-stubgen; extra == "ci"
Requires-Dist: openfermion; extra == "ci"
Requires-Dist: pytest; extra == "ci"
Provides-Extra: doc
Requires-Dist: mypy; extra == "doc"
Requires-Dist: pybind11-stubgen; extra == "doc"
Requires-Dist: sphinx==7.*; extra == "doc"
Requires-Dist: sphinx-rtd-theme; extra == "doc"
Requires-Dist: breathe; extra == "doc"
Requires-Dist: exhale; extra == "doc"
Requires-Dist: nbsphinx; extra == "doc"
Requires-Dist: myst-parser; extra == "doc"
Requires-Dist: sphinx-copybutton; extra == "doc"
Requires-Dist: ipykernel; extra == "doc"
Requires-Dist: sphinx-autoapi==3.0.0; extra == "doc"
Dynamic: license-file
